delphai_backend_utils/__init__.py
delphai_backend_utils/api_calls.py
delphai_backend_utils/caching.py
delphai_backend_utils/config.py
delphai_backend_utils/db_access.py
delphai_backend_utils/formatting.py
delphai_backend_utils/grpc_calls.py
delphai_backend_utils/logging.py
delphai_backend_utils/own_gateway.py
delphai_backend_utils/users.py
delphai_backend_utils-1.0.10.dist-info/LICENCE
delphai_backend_utils-1.0.10.dist-info/METADATA
delphai_backend_utils-1.0.10.dist-info/WHEEL
delphai_backend_utils-1.0.10.dist-info/top_level.txt
delphai_backend_utils-1.0.10.dist-info/RECORD
