Metadata-Version: 2.1
Name: delphai-backend-utils
Version: 1.0.10
Summary: A Python package to manage kube secrets.
Home-page: https://github.com/delphai/delphai-backend-utils
Author: Delphai
Author-email: ziyad@delphai.com
License: MIT
Platform: UNKNOWN
Classifier: License :: OSI Approved :: MIT License
Classifier: Programming Language :: Python :: 3
Classifier: Programming Language :: Python :: 3.7
License-File: LICENCE
Requires-Dist: omegaconf
Requires-Dist: memoization
Requires-Dist: azure-identity (==1.4.0b3)
Requires-Dist: azure-keyvault
Requires-Dist: python-dotenv
Requires-Dist: coloredlogs
Requires-Dist: kubernetes
Requires-Dist: keyring
